ismycomputeronfire/__init__.py
ismycomputeronfire/cli.py
ismycomputeronfire/fire_ascii.py
ismycomputeronfire/main.py
ismycomputeronfire/rules.py
ismycomputeronfire-0.4.dist-info/licenses/LICENSE
ismycomputeronfire-0.4.dist-info/METADATA
ismycomputeronfire-0.4.dist-info/WHEEL
ismycomputeronfire-0.4.dist-info/entry_points.txt
ismycomputeronfire-0.4.dist-info/top_level.txt
ismycomputeronfire-0.4.dist-info/RECORD
