Metadata-Version: 2.4
Name: ismycomputeronfire
Version: 0.4
Summary: A command-line tool to check if your computer is on fire.
License-File: LICENSE
Dynamic: description
Dynamic: description-content-type
Dynamic: license-file
Dynamic: summary
